Metadata-Version: 1.1
Name: sphinxembeddedvideos
Version: 1.1.0.dev20190210
Summary: Sphinx extension to embed Youtube videos.
Home-page: https://github.com/Peque/sphinxembeddedvideos
Author: Chris Pickel
Author-email: sfiera@gmail.com
License: BSD
Download-URL: https://pypi.org/project/sphinxembeddedvideos
Platform: any
Classifier: Development Status :: 4 - Beta
Classifier: Environment :: Console
Classifier: Environment :: Web Environment
Classifier: Intended Audience :: Developers
Classifier: License :: OSI Approved :: BSD License
Classifier: Operating System :: OS Independent
Classifier: Programming Language :: Python
Classifier: Topic :: Documentation
Classifier: Topic :: Utilities
